chunked_upload/__init__.py
chunked_upload/admin.py
chunked_upload/constants.py
chunked_upload/exceptions.py
chunked_upload/models.py
chunked_upload/response.py
chunked_upload/settings.py
chunked_upload/tests.py
chunked_upload/views.py
chunked_upload/management/__init__.py
chunked_upload/migrations/0001_initial.py
chunked_upload/migrations/__init__.py
django_chunked_upload-2.0.0.dist-info/LICENSE.txt
django_chunked_upload-2.0.0.dist-info/METADATA
django_chunked_upload-2.0.0.dist-info/WHEEL
django_chunked_upload-2.0.0.dist-info/top_level.txt
django_chunked_upload-2.0.0.dist-info/RECORD
