Metadata-Version: 1.1
Name: django-chunked-upload
Version: 2.0.0
Summary: Upload large files to Django in multiple chunks, with the ability to resume if the upload is interrupted.
Home-page: https://github.com/juliomalegria/django-chunked-upload
Author: Julio M Alegria
Author-email: juliomalegria@gmail.com
License: MIT-Zero
Download-URL: https://github.com/juliomalegria/django-chunked-upload/tarball/2.0.0
Platform: UNKNOWN
